connectus/__init__.py
connectus/architecture.py
connectus/controller/__init__.py
connectus/controller/creator/__init__.py
connectus/controller/creator/creator.py
connectus/controller/manager/__init__.py
connectus/controller/manager/manager.py
connectus/controller/type/__init__.py
connectus/controller/type/base/__init__.py
connectus/controller/type/base/base.py
connectus/controller/type/base/configuration/__init__.py
connectus/controller/type/base/configuration/configuration.py
connectus/controller/type/base/layers/__init__.py
connectus/controller/type/base/layers/acquisition/__init__.py
connectus/controller/type/base/layers/acquisition/acquisition.py
connectus/controller/type/base/layers/data_processing/__init__.py
connectus/controller/type/base/layers/data_processing/data_processing.py
connectus/controller/type/base/layers/dispatch/__init__.py
connectus/controller/type/base/layers/dispatch/dispatch.py
connectus/controller/type/base/layers/model/__init__.py
connectus/controller/type/base/layers/model/model.py
connectus/controller/type/base/layers/model/connectivity/__init__.py
connectus/data_manager/__init__.py
connectus/data_manager/data_manager.py
connectus/data_manager/node/__init__.py
connectus/data_manager/node/creator/__init__.py
connectus/data_manager/node/creator/creator.py
connectus/data_manager/node/type/__init__.py
connectus/data_manager/node/type/base/__init__.py
connectus/data_manager/node/type/base/base_node.py
connectus/data_manager/node/type/custom/__init__.py
connectus/data_manager/node/type/custom/influxdb/__init__.py
connectus/data_manager/node/type/custom/influxdb/influxdb.py
connectus/data_manager/node/type/custom/influxdb/configuration/__init__.py
connectus/data_manager/node/type/custom/influxdb/configuration/configuration.py
connectus/data_manager/node/type/custom/influxdb/layers/__init__.py
connectus/data_manager/node/type/custom/influxdb/layers/data_processing/__init__.py
connectus-0.0.21.dist-info/METADATA
connectus-0.0.21.dist-info/WHEEL
connectus-0.0.21.dist-info/top_level.txt
connectus-0.0.21.dist-info/RECORD
