Metadata-Version: 2.1
Name: connectus
Version: 0.0.21
Summary: Librería para la gestión de dispositivos físicos y virtuales.
Home-page: https://github.com/javierquinttana
Author: Javier A. Quintana Hernandez
Author-email: javierquinttana@gmail.com
License: MIT
Requires-Dist: pyserial
Requires-Dist: asyncua
Requires-Dist: cryptography
Requires-Dist: aiohttp
Requires-Dist: aiocsv
Requires-Dist: pandas
Requires-Dist: numpy
Requires-Dist: matplotlib
Requires-Dist: asyncpg
Requires-Dist: pyvisa
Requires-Dist: psutil
Requires-Dist: zeroconf
Requires-Dist: paho-mqtt
Requires-Dist: influxdb-client
